{	"root": [		{			"field_id": "122C9E72014C4F98AF85B1819EA0888A",			"field_number": 1,			"include": true,			"tetris_sort": 1,			"version_id": "FB35EB4590ED419BA16783D5C62E4404",			"version_number": 2,			"unique_path": "ascendco.sup.2.id",			"ib_table_name": "Sup",			"ib_field_name": "ID",			"pg_column_name": "id",			"system_field_name": "",			"ib_value_source_hint": "",			"ib_data_source_name": "field",			"ib_field_type_name": "Alpha Field",			"ib_field_type_hint": "",			"pg_type_hint": "",			"pg_type_guess": "uuid",			"conversion_method_name": "PgConvert_UUID_ToPG_For_INSERT"		},		{			"field_id": "8D296C430FE94AFFAD6275A6F67AB5F9",			"field_number": 14,			"include": true,			"tetris_sort": 1,			"version_id": "FB35EB4590ED419BA16783D5C62E4404",			"version_number": 2,			"unique_path": "ascendco.sup.2.custom_facility_id",			"ib_table_name": "Sup",			"ib_field_name": "CustomFacilityID",			"pg_column_name": "custom_facility_id",			"system_field_name": "",			"ib_value_source_hint": "",			"ib_data_source_name": "field",			"ib_field_type_name": "Alpha Field",			"ib_field_type_hint": "",			"pg_type_hint": "",			"pg_type_guess": "uuid",			"conversion_method_name": "PgConvert_UUID_ToPG_For_INSERT"		},		{			"field_id": "AF7ED80A5AD14F2D9AA5F42472C8F888",			"field_number": 18,			"include": true,			"tetris_sort": 1,			"version_id": "FB35EB4590ED419BA16783D5C62E4404",			"version_number": 2,			"unique_path": "ascendco.sup.2.sup_parent_id",			"ib_table_name": "Sup",			"ib_field_name": "SupParentID",			"pg_column_name": "sup_parent_id",			"system_field_name": "",			"ib_value_source_hint": "",			"ib_data_source_name": "field",			"ib_field_type_name": "Alpha Field",			"ib_field_type_hint": "",			"pg_type_hint": "",			"pg_type_guess": "uuid",			"conversion_method_name": "PgConvert_UUID_ToPG_For_INSERT"		},		{			"field_id": "075044F82D524B6898040F20A676F90A",			"field_number": 8,			"include": true,			"tetris_sort": 10,			"version_id": "FB35EB4590ED419BA16783D5C62E4404",			"version_number": 2,			"unique_path": "ascendco.sup.2.created_dts",			"ib_table_name": "Sup",			"ib_field_name": "CreatedDTS",			"pg_column_name": "created_dts",			"system_field_name": "",			"ib_value_source_hint": "",			"ib_data_source_name": "field",			"ib_field_type_name": "Alpha Field",			"ib_field_type_hint": "",			"pg_type_hint": "",			"pg_type_guess": "timestamp",			"conversion_method_name": "PgConvert_DTS_ToPG"		},		{			"field_id": "AD6E452BA9CB415D928DB70BF856846A",			"field_number": 9,			"include": true,			"tetris_sort": 10,			"version_id": "FB35EB4590ED419BA16783D5C62E4404",			"version_number": 2,			"unique_path": "ascendco.sup.2.updated_dts",			"ib_table_name": "Sup",			"ib_field_name": "UpdatedDTS",			"pg_column_name": "updated_dts",			"system_field_name": "",			"ib_value_source_hint": "",			"ib_data_source_name": "field",			"ib_field_type_name": "Alpha Field",			"ib_field_type_hint": "",			"pg_type_hint": "",			"pg_type_guess": "timestamp",			"conversion_method_name": "PgConvert_DTS_ToPG"		},		{			"field_id": "2C90BA51DE6547B9B6DFF1FF73B3E33D",			"field_number": 13,			"include": true,			"tetris_sort": 50,			"version_id": "FB35EB4590ED419BA16783D5C62E4404",			"version_number": 2,			"unique_path": "ascendco.sup.2.is_custom_by_facility",			"ib_table_name": "Sup",			"ib_field_name": "isCustomByFacility",			"pg_column_name": "is_custom_by_facility",			"system_field_name": "",			"ib_value_source_hint": "",			"ib_data_source_name": "field",			"ib_field_type_name": "Boolean",			"ib_field_type_hint": "",			"pg_type_hint": "",			"pg_type_guess": "boolean",			"conversion_method_name": "PgConvert_Boolean_ToPG"		},		{			"field_id": "E574FBA2BCC549909FDC898B14F18C7F",			"field_number": 3,			"include": true,			"tetris_sort": 50,			"version_id": "FB35EB4590ED419BA16783D5C62E4404",			"version_number": 2,			"unique_path": "ascendco.sup.2.marked_for_deletion",			"ib_table_name": "Sup",			"ib_field_name": "DeletedRecordDate",			"pg_column_name": "marked_for_deletion",			"system_field_name": "",			"ib_value_source_hint": "",			"ib_data_source_name": "system_field",			"ib_field_type_name": "Date",			"ib_field_type_hint": "",			"pg_type_hint": "",			"pg_type_guess": "boolean",			"conversion_method_name": "PgConvert_DateIsNotEmpty_ToPG"		},		{			"field_id": "136A119E8AAE454D9CF0A53442956E54",			"field_number": 19,			"include": true,			"tetris_sort": 50,			"version_id": "FB35EB4590ED419BA16783D5C62E4404",			"version_number": 2,			"unique_path": "ascendco.sup.2.is_available_for_loaners",			"ib_table_name": "Sup",			"ib_field_name": "isAvailableForLoaners",			"pg_column_name": "is_available_for_loaners",			"system_field_name": "",			"ib_value_source_hint": "",			"ib_data_source_name": "field",			"ib_field_type_name": "Boolean",			"ib_field_type_hint": "",			"pg_type_hint": "",			"pg_type_guess": "boolean",			"conversion_method_name": "PgConvert_Boolean_ToPG"		},		{			"field_id": "67BC4EBED32C4927A5DEC1EA75B3FB1B",			"field_number": 2,			"include": true,			"tetris_sort": 60,			"version_id": "FB35EB4590ED419BA16783D5C62E4404",			"version_number": 2,			"unique_path": "ascendco.sup.2.name_",			"ib_table_name": "Sup",			"ib_field_name": "Name",			"pg_column_name": "name_",			"system_field_name": "",			"ib_value_source_hint": "",			"ib_data_source_name": "field",			"ib_field_type_name": "Alpha Field",			"ib_field_type_hint": "",			"pg_type_hint": "",			"pg_type_guess": "citext",			"conversion_method_name": "PgConvert_Text_ToPG"		},		{			"field_id": "24DE3A973D174831A474917089A89DCE",			"field_number": 10,			"include": true,			"tetris_sort": 60,			"version_id": "FB35EB4590ED419BA16783D5C62E4404",			"version_number": 2,			"unique_path": "ascendco.sup.2.created_by",			"ib_table_name": "Sup",			"ib_field_name": "CreatedBy",			"pg_column_name": "created_by",			"system_field_name": "",			"ib_value_source_hint": "",			"ib_data_source_name": "field",			"ib_field_type_name": "Alpha Field",			"ib_field_type_hint": "",			"pg_type_hint": "",			"pg_type_guess": "citext",			"conversion_method_name": "PgConvert_Text_ToPG"		},		{			"field_id": "134DBB74769F4C2197EBC22BE74FED53",			"field_number": 11,			"include": true,			"tetris_sort": 60,			"version_id": "FB35EB4590ED419BA16783D5C62E4404",			"version_number": 2,			"unique_path": "ascendco.sup.2.updated_by",			"ib_table_name": "Sup",			"ib_field_name": "UpdatedBy",			"pg_column_name": "updated_by",			"system_field_name": "",			"ib_value_source_hint": "",			"ib_data_source_name": "field",			"ib_field_type_name": "Alpha Field",			"ib_field_type_hint": "",			"pg_type_hint": "",			"pg_type_guess": "citext",			"conversion_method_name": "PgConvert_Text_ToPG"		},		{			"field_id": "C3449AE91BAD48DAB75BF820BAEB7618",			"field_number": 12,			"include": true,			"tetris_sort": 60,			"version_id": "FB35EB4590ED419BA16783D5C62E4404",			"version_number": 2,			"unique_path": "ascendco.sup.2.short_name",			"ib_table_name": "Sup",			"ib_field_name": "ShortName",			"pg_column_name": "short_name",			"system_field_name": "",			"ib_value_source_hint": "",			"ib_data_source_name": "field",			"ib_field_type_name": "Alpha Field",			"ib_field_type_hint": "",			"pg_type_hint": "",			"pg_type_guess": "citext",			"conversion_method_name": "PgConvert_Text_ToPG"		}	]}